coggle_ecs/__init__.py
coggle_ecs/parser.py
coggle_ecs-0.0.3.dist-info/LICENSE
coggle_ecs-0.0.3.dist-info/METADATA
coggle_ecs-0.0.3.dist-info/WHEEL
coggle_ecs-0.0.3.dist-info/top_level.txt
coggle_ecs-0.0.3.dist-info/RECORD
