Metadata-Version: 2.1
Name: coggle-ecs
Version: 0.0.3
Summary: Convert Coggle .mm files to ECS tables and whatnot
Home-page: https://github.com/MrGVSV/coggle-ecs
Author: Gino Valente
Author-email: gino.valente.code@gmail.com
License: MIT
Platform: UNKNOWN
Requires-Python: >=3.6
Requires-Dist: pandas
